x2webrtc/__init__.py
x2webrtc/cli.py
x2webrtc/config.py
x2webrtc/input.py
x2webrtc/models.py
x2webrtc/plugin.py
x2webrtc/py.typed
x2webrtc/screen_capture.py
x2webrtc/signaling.py
x2webrtc/timer.py
x2webrtc/track.py
x2webrtc/webrtc.py
x2webrtc-0.2.0.dist-info/METADATA
x2webrtc-0.2.0.dist-info/WHEEL
x2webrtc-0.2.0.dist-info/entry_points.txt
x2webrtc-0.2.0.dist-info/top_level.txt
x2webrtc-0.2.0.dist-info/RECORD
