Metadata-Version: 2.1
Name: x2webrtc
Version: 0.2.0
Summary: Forward X window through WebRTC as a MediaStream
Home-page: https://github.com/bonprosoft/x2webrtc
Author: Yuki Igarashi
Author-email: me@bonprosoft.com
License: MIT License
Platform: UNKNOWN
Classifier: Programming Language :: Python :: 3.6
Classifier: Programming Language :: Python :: 3.7
Classifier: Programming Language :: Python :: 3.8
Classifier: Programming Language :: Python :: 3.9
Classifier: Programming Language :: Python
Classifier: License :: OSI Approved :: MIT License
Requires-Dist: Pillow (<7.1.0,>=7.0.0)
Requires-Dist: PyYAML (<6.0.0,>=5.0.0)
Requires-Dist: aiortc (<0.10.0,>=0.9.0)
Requires-Dist: av (<8.0.0,>=7.0.0)
Requires-Dist: dacite (<1.3.0,>=1.2.0)
Requires-Dist: numpy (<1.19.0,>=1.18.0)
Requires-Dist: python-xlib (<1.0,>=0.26)
Requires-Dist: dataclasses ; python_version < "3.7"
Provides-Extra: test
Requires-Dist: pytest (<6.0.0,>=5.0.0) ; extra == 'test'
Requires-Dist: pytest-asyncio (<1.0.0,>=0.10.0) ; extra == 'test'
